setup.py
lazychannel/__init__.py
lazychannel/cli.py
lazychannel/config.py
lazychannel/generate.py
lazychannel/helpers.py
lazychannel/sync.py
lazychannel.egg-info/PKG-INFO
lazychannel.egg-info/SOURCES.txt
lazychannel.egg-info/dependency_links.txt
lazychannel.egg-info/entry_points.txt
lazychannel.egg-info/requires.txt
lazychannel.egg-info/top_level.txt
lazychannel/processor/__init__.py
lazychannel/processor/youtube.py