Metadata-Version: 1.1
Name: lazychannel
Version: 0.1.3
Summary: Fetch media from remote sources daily!
Home-page: https://github.com/chuckbutler/lazychannel
Author: Charles Butler
Author-email: chuck@dasroot.net
License: LGPLv3
Download-URL: https://github.com/chuckbutler/lazychannel/tarball/v0.1.3
Platform: UNKNOWN
Classifier: Development Status :: 3 - Alpha
Classifier: License :: OSI Approved :: GNU Lesser General Public License v3 (LGPLv3)
Classifier: Environment :: Console
Classifier: Topic :: Multimedia :: Sound/Audio
